{
	"info": {
		"_postman_id": "df571715-410d-41d4-b5c5-19e5be1ef62f",
		"name": "https://orange-backend.ml",
		"schema": "https://schema.getpostman.com/json/collection/v2.1.0/collection.json"
	},
	"item": [
		{
			"name": "auth",
			"item": [
				{
					"name": "{{url}}/api/auth/login",
					"request": {
						"auth": {
							"type": "basic",
							"basic": [
								{
									"key": "username",
									"value": "test2",
									"type": "string"
								},
								{
									"key": "password",
									"value": "password",
									"type": "string"
								}
							]
						},
						"method": "POST",
						"header": [
							{
								"key": "Secure-Api-Key",
								"value": "{{Secure-Api-Key}}"
							},
							{
								"key": "Content-Type",
								"value": "application/json"
							}
						],
						"body": {
							"mode": "raw",
							"raw": ""
						},
						"url": {
							"raw": "{{url}}/api/auth/login",
							"host": [
								"{{url}}"
							],
							"path": [
								"api",
								"auth",
								"login"
							]
						},
						"description": "getting token"
					},
					"response": []
				}
			]
		},
		{
			"name": "user",
			"item": [
				{
					"name": "{{url}}/api/user",
					"request": {
						"method": "POST",
						"header": [
							{
								"key": "Secure-Api-Key",
								"value": "{{Secure-Api-Key}}"
							},
							{
								"key": "Content-Type",
								"value": "application/json"
							}
						],
						"body": {
							"mode": "raw",
							"raw": "{\r\n    \"login\": \"test2\",\r\n    \"password\": \"password\"\r\n}"
						},
						"url": {
							"raw": "{{url}}/api/user",
							"host": [
								"{{url}}"
							],
							"path": [
								"api",
								"user"
							]
						},
						"description": "user1"
					},
					"response": []
				},
				{
					"name": "{{url}}/api/user/all",
					"protocolProfileBehavior": {
						"disableBodyPruning": true
					},
					"request": {
						"auth": {
							"type": "noauth"
						},
						"method": "GET",
						"header": [
							{
								"key": "Secure-Api-Key",
								"value": "{{Secure-Api-Key}}"
							},
							{
								"key": "Content-Type",
								"value": "application/json"
							}
						],
						"body": {
							"mode": "raw",
							"raw": ""
						},
						"url": {
							"raw": "{{url}}/api/user/all",
							"host": [
								"{{url}}"
							],
							"path": [
								"api",
								"user",
								"all"
							]
						},
						"description": "get users with token"
					},
					"response": []
				},
				{
					"name": "{{url}}/api/user/1",
					"protocolProfileBehavior": {
						"disableBodyPruning": true
					},
					"request": {
						"method": "GET",
						"header": [
							{
								"key": "Secure-Api-Key",
								"value": "{{Secure-Api-Key}}"
							},
							{
								"key": "Content-Type",
								"value": "application/json"
							}
						],
						"body": {
							"mode": "raw",
							"raw": ""
						},
						"url": {
							"raw": "{{url}}/api/user/1",
							"host": [
								"{{url}}"
							],
							"path": [
								"api",
								"user",
								"1"
							]
						}
					},
					"response": []
				},
				{
					"name": "{{url}}/api/user/1",
					"request": {
						"auth": {
							"type": "bearer",
							"bearer": [
								{
									"key": "token",
									"value": "sxt51VNvKvpTlAIFah0zJpMEJBZICtj8",
									"type": "string"
								}
							]
						},
						"method": "PUT",
						"header": [
							{
								"key": "Secure-Api-Key",
								"value": "{{Secure-Api-Key}}"
							},
							{
								"key": "Content-Type",
								"value": "application/json"
							}
						],
						"body": {
							"mode": "raw",
							"raw": "{\n    \"login\": \"test3\"\n}"
						},
						"url": {
							"raw": "{{url}}/api/user/7",
							"host": [
								"{{url}}"
							],
							"path": [
								"api",
								"user",
								"7"
							]
						},
						"description": "Put"
					},
					"response": []
				},
				{
					"name": "{{url}}/api/user/2",
					"request": {
						"auth": {
							"type": "bearer",
							"bearer": [
								{
									"key": "token",
									"value": "TytksUT4TKn/ybSKVrEbGS7Wlv01JtrM",
									"type": "string"
								}
							]
						},
						"method": "DELETE",
						"header": [
							{
								"key": "Secure-Api-Key",
								"value": "{{Secure-Api-Key}}"
							},
							{
								"key": "Content-Type",
								"value": "application/json"
							}
						],
						"body": {
							"mode": "raw",
							"raw": ""
						},
						"url": {
							"raw": "{{url}}/api/user/2",
							"host": [
								"{{url}}"
							],
							"path": [
								"api",
								"user",
								"2"
							]
						}
					},
					"response": []
				}
			]
		},
		{
			"name": "admin",
			"item": [
				{
					"name": "{{url}}/api/admin",
					"request": {
						"method": "POST",
						"header": [
							{
								"key": "Secure-Api-Key",
								"value": "{{Secure-Api-Key}}"
							},
							{
								"key": "Content-Type",
								"value": "application/json"
							}
						],
						"body": {
							"mode": "raw",
							"raw": "{\r\n    \"full_name\": \"admintest2\"\r\n}"
						},
						"url": {
							"raw": "{{url}}/api/admin",
							"host": [
								"{{url}}"
							],
							"path": [
								"api",
								"admin"
							]
						},
						"description": "user1"
					},
					"response": []
				},
				{
					"name": "{{url}}/api/admin/all",
					"protocolProfileBehavior": {
						"disableBodyPruning": true
					},
					"request": {
						"auth": {
							"type": "noauth"
						},
						"method": "GET",
						"header": [
							{
								"key": "Secure-Api-Key",
								"value": "{{Secure-Api-Key}}"
							},
							{
								"key": "Content-Type",
								"value": "application/json"
							}
						],
						"body": {
							"mode": "raw",
							"raw": ""
						},
						"url": {
							"raw": "{{url}}/api/admin/all",
							"host": [
								"{{url}}"
							],
							"path": [
								"api",
								"admin",
								"all"
							]
						},
						"description": "get users with token"
					},
					"response": []
				},
				{
					"name": "{{url}}/api/admin/1",
					"protocolProfileBehavior": {
						"disableBodyPruning": true
					},
					"request": {
						"method": "GET",
						"header": [
							{
								"key": "Secure-Api-Key",
								"value": "{{Secure-Api-Key}}"
							},
							{
								"key": "Content-Type",
								"value": "application/json"
							}
						],
						"body": {
							"mode": "raw",
							"raw": ""
						},
						"url": {
							"raw": "{{url}}/api/admin/3",
							"host": [
								"{{url}}"
							],
							"path": [
								"api",
								"admin",
								"3"
							]
						}
					},
					"response": []
				},
				{
					"name": "{{url}}/api/admin/1",
					"request": {
						"auth": {
							"type": "bearer",
							"bearer": [
								{
									"key": "token",
									"value": "sxt51VNvKvpTlAIFah0zJpMEJBZICtj8",
									"type": "string"
								}
							]
						},
						"method": "PUT",
						"header": [
							{
								"key": "Secure-Api-Key",
								"value": "{{Secure-Api-Key}}"
							},
							{
								"key": "Content-Type",
								"value": "application/json"
							}
						],
						"body": {
							"mode": "raw",
							"raw": "{\n    \"full_name\": \"test3admin\"\n}"
						},
						"url": {
							"raw": "{{url}}/api/admin/3",
							"host": [
								"{{url}}"
							],
							"path": [
								"api",
								"admin",
								"3"
							]
						},
						"description": "Put"
					},
					"response": []
				},
				{
					"name": "{{url}}/api/admin/2",
					"request": {
						"auth": {
							"type": "bearer",
							"bearer": [
								{
									"key": "token",
									"value": "TytksUT4TKn/ybSKVrEbGS7Wlv01JtrM",
									"type": "string"
								}
							]
						},
						"method": "DELETE",
						"header": [
							{
								"key": "Secure-Api-Key",
								"value": "{{Secure-Api-Key}}"
							},
							{
								"key": "Content-Type",
								"value": "application/json"
							}
						],
						"body": {
							"mode": "raw",
							"raw": ""
						},
						"url": {
							"raw": "{{url}}/api/admin/2",
							"host": [
								"{{url}}"
							],
							"path": [
								"api",
								"admin",
								"2"
							]
						}
					},
					"response": []
				}
			]
		},
		{
			"name": "company",
			"item": [
				{
					"name": "{{url}}/api/company",
					"request": {
						"method": "POST",
						"header": [
							{
								"key": "Secure-Api-Key",
								"value": "{{Secure-Api-Key}}"
							},
							{
								"key": "Content-Type",
								"value": "application/json"
							}
						],
						"body": {
							"mode": "raw",
							"raw": "{\r\n    \"full_name\": \"companytest2\"\r\n}"
						},
						"url": {
							"raw": "{{url}}/api/company",
							"host": [
								"{{url}}"
							],
							"path": [
								"api",
								"company"
							]
						},
						"description": "user1"
					},
					"response": []
				},
				{
					"name": "{{url}}/api/company/all",
					"protocolProfileBehavior": {
						"disableBodyPruning": true
					},
					"request": {
						"auth": {
							"type": "noauth"
						},
						"method": "GET",
						"header": [
							{
								"key": "Secure-Api-Key",
								"value": "{{Secure-Api-Key}}"
							},
							{
								"key": "Content-Type",
								"value": "application/json"
							}
						],
						"body": {
							"mode": "raw",
							"raw": ""
						},
						"url": {
							"raw": "{{url}}/api/company/all",
							"host": [
								"{{url}}"
							],
							"path": [
								"api",
								"company",
								"all"
							]
						},
						"description": "get users with token"
					},
					"response": []
				},
				{
					"name": "{{url}}/api/company/1",
					"protocolProfileBehavior": {
						"disableBodyPruning": true
					},
					"request": {
						"method": "GET",
						"header": [
							{
								"key": "Secure-Api-Key",
								"value": "{{Secure-Api-Key}}"
							},
							{
								"key": "Content-Type",
								"value": "application/json"
							}
						],
						"body": {
							"mode": "raw",
							"raw": ""
						},
						"url": {
							"raw": "{{url}}/api/company/3",
							"host": [
								"{{url}}"
							],
							"path": [
								"api",
								"company",
								"3"
							]
						}
					},
					"response": []
				},
				{
					"name": "{{url}}/api/company/1",
					"request": {
						"auth": {
							"type": "bearer",
							"bearer": [
								{
									"key": "token",
									"value": "sxt51VNvKvpTlAIFah0zJpMEJBZICtj8",
									"type": "string"
								}
							]
						},
						"method": "PUT",
						"header": [
							{
								"key": "Secure-Api-Key",
								"value": "{{Secure-Api-Key}}"
							},
							{
								"key": "Content-Type",
								"value": "application/json"
							}
						],
						"body": {
							"mode": "raw",
							"raw": "{\n    \"full_name\": \"test3admin\"\n}"
						},
						"url": {
							"raw": "{{url}}/api/company/3",
							"host": [
								"{{url}}"
							],
							"path": [
								"api",
								"company",
								"3"
							]
						},
						"description": "Put"
					},
					"response": []
				},
				{
					"name": "{{url}}/api/company/2",
					"request": {
						"auth": {
							"type": "bearer",
							"bearer": [
								{
									"key": "token",
									"value": "TytksUT4TKn/ybSKVrEbGS7Wlv01JtrM",
									"type": "string"
								}
							]
						},
						"method": "DELETE",
						"header": [
							{
								"key": "Secure-Api-Key",
								"value": "{{Secure-Api-Key}}"
							},
							{
								"key": "Content-Type",
								"value": "application/json"
							}
						],
						"body": {
							"mode": "raw",
							"raw": ""
						},
						"url": {
							"raw": "{{url}}/api/company/2",
							"host": [
								"{{url}}"
							],
							"path": [
								"api",
								"company",
								"2"
							]
						}
					},
					"response": []
				}
			]
		},
		{
			"name": "driver",
			"item": [
				{
					"name": "{{url}}/api/admin/driver",
					"request": {
						"method": "POST",
						"header": [
							{
								"key": "Secure-Api-Key",
								"value": "{{Secure-Api-Key}}"
							},
							{
								"key": "Content-Type",
								"value": "application/json"
							}
						],
						"body": {
							"mode": "raw",
							"raw": "{\r\n    \"full_name\": \"drivertest2\",\r\n    \"status\": \"occupied\"\r\n}"
						},
						"url": {
							"raw": "{{url}}/api/admin/driver",
							"host": [
								"{{url}}"
							],
							"path": [
								"api",
								"admin",
								"driver"
							]
						},
						"description": "user1"
					},
					"response": []
				},
				{
					"name": "{{url}}/api/admin/driver/all",
					"protocolProfileBehavior": {
						"disableBodyPruning": true
					},
					"request": {
						"auth": {
							"type": "noauth"
						},
						"method": "GET",
						"header": [
							{
								"key": "Secure-Api-Key",
								"value": "{{Secure-Api-Key}}"
							},
							{
								"key": "Content-Type",
								"value": "application/json"
							}
						],
						"body": {
							"mode": "raw",
							"raw": ""
						},
						"url": {
							"raw": "{{url}}/api/admin/driver/all",
							"host": [
								"{{url}}"
							],
							"path": [
								"api",
								"admin",
								"driver",
								"all"
							]
						},
						"description": "get users with token"
					},
					"response": []
				},
				{
					"name": "{{url}}/api/admin/driver/1",
					"protocolProfileBehavior": {
						"disableBodyPruning": true
					},
					"request": {
						"method": "GET",
						"header": [
							{
								"key": "Secure-Api-Key",
								"value": "{{Secure-Api-Key}}"
							},
							{
								"key": "Content-Type",
								"value": "application/json"
							}
						],
						"body": {
							"mode": "raw",
							"raw": ""
						},
						"url": {
							"raw": "{{url}}/api/admin/driver/3",
							"host": [
								"{{url}}"
							],
							"path": [
								"api",
								"admin",
								"driver",
								"3"
							]
						}
					},
					"response": []
				},
				{
					"name": "{{url}}/api/admin/driver/1",
					"request": {
						"auth": {
							"type": "bearer",
							"bearer": [
								{
									"key": "token",
									"value": "sxt51VNvKvpTlAIFah0zJpMEJBZICtj8",
									"type": "string"
								}
							]
						},
						"method": "PUT",
						"header": [
							{
								"key": "Secure-Api-Key",
								"value": "{{Secure-Api-Key}}"
							},
							{
								"key": "Content-Type",
								"value": "application/json"
							}
						],
						"body": {
							"mode": "raw",
							"raw": "{\r\n    \"full_name\": \"drivertest2344\",\r\n    \"status\": \"occupied\"\r\n}"
						},
						"url": {
							"raw": "{{url}}/api/admin/driver/3",
							"host": [
								"{{url}}"
							],
							"path": [
								"api",
								"admin",
								"driver",
								"3"
							]
						},
						"description": "Put"
					},
					"response": []
				},
				{
					"name": "{{url}}/api/admin/driver/2",
					"request": {
						"auth": {
							"type": "bearer",
							"bearer": [
								{
									"key": "token",
									"value": "TytksUT4TKn/ybSKVrEbGS7Wlv01JtrM",
									"type": "string"
								}
							]
						},
						"method": "DELETE",
						"header": [
							{
								"key": "Secure-Api-Key",
								"value": "{{Secure-Api-Key}}"
							},
							{
								"key": "Content-Type",
								"value": "application/json"
							}
						],
						"body": {
							"mode": "raw",
							"raw": ""
						},
						"url": {
							"raw": "{{url}}/api/admin/driver/2",
							"host": [
								"{{url}}"
							],
							"path": [
								"api",
								"admin",
								"driver",
								"2"
							]
						}
					},
					"response": []
				}
			]
		}
	]
}