{
  "title": "Update item",
  "description": "Update a item object",
  "type": "object",
  "$schema": "http://json-schema.org/draft-04/schema",
  "properties": {
    "name": {
      "type": "string"
    },
    "pickup_date": {
      "type": "string"
    },
    "pickup_address": {
      "type": "string"
    },
    "kst": {
      "type": "string"
    },
    "orderer_name": {
      "type": "string"
    },
    "message": {
      "type": "string"
    },
    "n_stops": {
      "type": "string"
    },
    "destination": {
      "type": "string"
    },
    "price": {
      "type": "string"
    }
  },
  "additionalProperties": false
}
